dv_flow/libpss/__ext__.py
dv_flow/libpss/__init__.py
dv_flow/libpss/flow.dv
dv_flow/libpss/flow_psp.dv
dv_flow/libpss/flow_vcp.dv
dv_flow/libpss/flow_zsp.dv
dv_flow/libpss/psp_gen_actor_sv.py
dv_flow/libpss/psp_gen_model_sv.py
dv_flow/libpss/psp_lib.py
dv_flow/libpss/psp_log_parser.py
dv_flow/libpss/psp_runtime_sv.py
dv_flow/libpss/zsp_gen_actor_sv.py
dv_flow/libpss/zsp_gen_model_sv.py
dv_flow/libpss/zsp_runtime_sv.py
dv_flow_libpss-0.0.114939575656rc0.dist-info/licenses/LICENSE
dv_flow_libpss-0.0.114939575656rc0.dist-info/METADATA
dv_flow_libpss-0.0.114939575656rc0.dist-info/WHEEL
dv_flow_libpss-0.0.114939575656rc0.dist-info/entry_points.txt
dv_flow_libpss-0.0.114939575656rc0.dist-info/top_level.txt
dv_flow_libpss-0.0.114939575656rc0.dist-info/RECORD
