Metadata-Version: 2.4
Name: dv-flow-libpss
Version: 0.0.114939575656rc0
Summary: Provides dv-flow tasks for performing common tasks related to Accellera PSS
Author-email: Matthew Ballance <matt.ballance@gmail.com>
License:                                  Apache License
License-File: LICENSE
Requires-Dist: dv-flow-mgr
Dynamic: license-file
